{
  "success": true,
  "language_code": "guj",
  "language_label": "ગુજરાતી",
  "topics_text": "1. ભારતનો સાંસ્કૃતિક વારસો : શિલ્પ અને સ્થાપત્ય  \n- શિલ્પકલા: “શિલ્પી પોતાનાં કૌશલ્ય અને આવડતને છીણી‑હથોડી વડે વિવિધ પ્રકારના મનના ભાવો પથ્થર, લાકડું કે ધાતુમાં કંડારે તે કલા એટલે શિલ્પકલા.”  \n- સ્થાપત્ય: “સ્થાપત્યનો સરળ અર્થ બાંધકામ એવો થાય છે. સંસ્કૃત ભાષામાં સ્થાપત્ય માટે ‘ard? શબ્દ વપરાય છે, જે ખૂબ જ પ્રચલિત છે. આ અર્થમાં મકાનો, નગરો, કૂવાઓ, કિલ્લાઓ, મિનારાઓ, મંદિરો, મસ્જિદો, મકબરાઓ વગેરેના બાંધકામને ‘સ્થાપત્ય' કહે છે. સ્થાપત્યકલામાં ‘સ્થપતિ’નું કૌશલ્ય પ્રયોજાય છે.”\n\n2. પ્રાચીન ભારતનું નગર આયોજન  \n- મુખ્ય વિભાગો: “આ નગરોના મુખ્ય ત્રણ વિભાગો પડે છે : (1) શાસક અધિકારીઓનો ગઢ (સિટડલ) (2) અન્ય અધિકારીઓના આવાસો ધરાવતું ઉપલું નગર (3) સામાન્ય નગરજનોના આવાસ ધરાવતું lad નગર.”  \n- ગઢ અને ઉપલું નગર: “શાસક અધિકારીઓનો ગઢ જે ઊંચાઈ ઉપર બાંધવામાં આવ્યો છે. ઉપલું નગર પણ રક્ષણાત્મક દીવાલોથી સુરક્ષિત છે. અહીંથી બેથી પાંચ ઓરડાવાળા મકાનો મળી આવ્યા છે.”  \n- નગરની રચના: “નીચલા નગરનાં મકાનો મુખ્યત્વે હાથે ઘડેલી ઈંટોનાં બનાવેલાં છે.”  \n\n3. મોહેં‑જો‑દડો  \n- નગર રચના: “મોહેં‑જો‑દડો નગર આયોજનની દૃષ્ટિએ શ્રેષ્ઠ હતું. મકાનો પૂર અને ભેજથી બચવા ઊંચી પ્લિંથ (પીઠિકા) ઉપર બાંધવામાં આવતાં હતાં. શ્રીમંતોનાં મકાનો બે માળવાળા અને પાંચ કે સાત ઓરડાવાળા હતાં. સામાન્ય વર્ગનાં મકાનો એક માળ અને બે કે ત્રણ ઓરડાવાળા હતાં.”  \n- રસ્તાઓ: “મોટે ભાગે 9.75 મીટર પહોળા રસ્તાઓ હતા. નાના‑મોટા રસ્તાઓ કાટખૂણે મળતા અને એકથી વધુ વાહનો પસાર થાય એટલા પહોળા હતા. નગરના સીધા પહોળા રાજમાર્ગો હતા, જે ક્યાંય વળાંક ન લેતાં સીધા જ જતા હતા.”  \n- ગટર યોજના: “નગરમાંથી ગંદા પાણીના નિકાલ માટે ગટર બનાવવામાં આવી હતી. દરેક મકાનમાં એક ખાળકૂવો હતો. આ સુવ્યવસ્થિત ગટર યોજના પરથી લાગે છે કે તેઓ સ્વચ્છતા તેમજ આરોગ્યના ઊંચા ખ્યાલો ધરાવતા હતા.”  \n- જાહેર સ્નાનાગાર: “વિશાળ સ્નાનાગાર મળી આવ્યું છે. સ્નાનકુંડમાં સ્વચ્છ પાણી દાખલ કરવા અને ગંદું પાણી બહાર કાઢવા માટેની વ્યવસ્થા હતી. ગરમ પાણીની વ્યવસ્થા અને વસ્ત્રો બદલવા માટે ઓરડીઓ મળી આવી છે.”  \n- જાહેર મકાનો: “મોહેં‑જો‑દડોમાંથી જાહેર ઉપયોગી બે મકાનો મળ્યાં છે. તેનો ઉપયોગ સભાખંડ, મનોરંજન ખંડ, વહીવટ ખંડ કે રાજ્યના કોઠાર ખંડ તરીકે થતો હશે. મકાનોની એક હરોળ સૈનિકો માટેની બેરેક હતી.”\n\n4. હડપ્પા  \n- હડપ્પીય સંસ્કૃતિ: “સૌપ્રથમ આ સંસ્કૃતિના અવશેષો હડપ્પા સ્થળેથી મળી આવેલા હોવાથી તેને હડપ્પીય સંસ્કૃતિ કહેવાય છે. આ સ્થળેથી પાષાણનાં અને તાંબાનાં ઓજારો, ચીજવસ્તુઓ વગેરે મળી આવ્યાં છે. તેથી તેને તામ્રપાષાણ યુગની સંસ્કૃતિ પણ કહે છે.”  \n- નગર આયોજન: “હડપ્પીય સમયનું નગરોનું આયોજન સુવ્યવસ્થિત હતું. તેના મોટા કોઠારો અને કિલ્લેબંધી નોંધપાત્ર છે. તેઓ અલંકારો ધારણ કરવાના શોખીન હતા, તેવા પુરાવાઓ મળ્યા છે.”\n\n5. ધોળાવીરા  \n- નગર અને કિલ્લાબંધી: “ધોળાવીરાના કિલ્લા, મહેલ તેમજ નગરની મુખ્ય અવશેષો મળી આવ્યા છે. નગરની કિલ્લેબંધીની મજબૂત સુરક્ષા વ્યવસ્થા છે. આ દીવાલ માટી, પથ્થર અને ઈંટોમાંથી બનેલી છે.”  \n- પાણીની વ્યવસ્થા: “અહીંથી પીવાનું પાણી શુદ્ધ ગળાઈને આવે તેવી વ્યવસ્થા કરવામાં આવી હતી, જે આજના આધુનિક યુગમાં પણ મુશ્કેલ છે.”\n\n6. લોથલ  \n- બંદર અને વેપાર: “લોથલ ધોળકા તાલુકામાં બે નદીઓના વચ્ચે આવેલું છે. નગરના પૂર્વ છેડે નીચાણવાળા ભાગમાં વહાણ લાંગરવા માટે મોટો ડોક્યાર્ડ બાંધવામાં આવ્યો હતો. આ ડોક્યાર્ડ, Wharf, દુકાનો, આયાત‑નિકાસના પુરાવા દર્શાવે છે કે લોથલ તે સમયનું સમૃદ્ધ બંદર હતું.”  \n\n7. મૌર્ય કાલીન કલા  \n- સ્તૂપ: “સ્તૂપ એટલે ભગવાન બુદ્ધના દેહાવશેષોને એક પાત્રમાં મૂકી તેના પર અર્ધગોળાકાર ઇમારતો બનાવવામાં આવે છે. અશોકના સમયના પાંચ સ્તૂપો જાણીતા છે: સાંચીનો, સારનાથનો, બેરતનો, નંદનગઢનો અને ગુજરાતમાં દેવની મોરીનો સ્તૂપ.”  \n- હર્મિકા, મેધિ, પ્રદક્ષિણા પથ, તોરણ, સ્તંભલેખો: “સ્તૂપની અંડાકાર ભાગની ટોચની ચારે બાજુએ આવેલી રેલિંગને ‘હર્મિકા’ કહે છે. સ્તૂપની ચારે બાજુએ ઊંચા ગોળાકાર રસ્તાને ‘AB’ કહે છે. ગોળાકાર રસ્તાને ‘પ્રદક્ષિણા પથ’ કહે છે. તોરણ એટલે બે સ્તંભ ઉપર સીધા પાટડા કે કમાનના આકારમાં પથ્થર આડા પાડી કરવામાં આવેલું સુંદર સ્થાપત્ય. સ્તંભલેખો એક જ શિલામાંથી કોતરવામાં આવ્યા છે, જેમ કે અશોકના ધર્માજ્ઞાઓ કોતરેલા સ્તંભો.”\n\n8. દક્ષિણ ભારતની દ્રવિડ શૈલી  \n- બૌદ્ધ સ્તૂપો: “દક્ષિણ ભારતમાં કૃષ્ણા અને ગોદાવરી નદીઓની આસપાસના વિસ્તારમાં સાતવાહન વંશના રાજાઓના સમય દરમિયાન અનેક બૌદ્ધ સ્તૂપો બંધાયા હતા. નાગાર્જુન કોંડાનો સ્તૂપ અને અમરાવતીનો સ્તૂપ દ્રવિડ શૈલીના સર્વશ્રેષ્ઠ નમૂનાઓ છે.”  \n\n9. ગુપ્તકાલીન કલા  \n- મુખ્ય સ્મારકો: “જબલપુરનું (નિનાવા) પાર્વતી મંદિર, ભૂમરા (નાગોડા)નું શિવમંદિર, એરણ (મધ્યપ્રદેશ)નું નૃસિંહ મંદિર, જામનગરનું ગોપમંદિર, Aul ચૈત્યો, મઠો, વિહારો, ધ્વજ, સ્તંભો વગેરે ગુપ્તયુગની કલાઓના નમૂના છે.”  \n- શિલ્પ: “સારનાથની બુદ્ધ પ્રતિમાઓ, મથુરાની વિષ્ણુ પ્રતિમા, મહાવીર સ્વામીની પ્રતિમા, ઉદયગિરિની ગુફાની, વિષ્ણુના વરાહ સ્વરૂપની પ્રતિમા વગેરે ભારતીય ગુપ્તકાલીન કલાના સર્વોત્તમ નમૂનાઓને લીધે ગુપ્તયુગ કલાનો ‘સુવર્ણયુગ’ કહેવાય છે.”\n\n10. ગુફા સ્થાપત્ય (ગુફાઓ)  \n- પ્રસિદ્ધ ગુફાઓ: “ઔરંગાબાદ પાસે આવેલ અજંતા‑ઈલોરાની ગુફાઓ, મુંબઈ પાસેની એલિફન્ટાની ગુફાઓ, ઓડિશામાં ભુવનેશ્વરની પશ્ચિમે ઉદયગિરિ, ખંડગિરિ ગુફાઓ, મધ્યપ્રદેશની બાઘની ગુફાઓ, ગુપ્તકાલીન ગુફાસ્થાપત્યના પ્રસિદ્ધ નમૂનાઓ છે.”  \n- ગુજરાતની ગુફાઓ: “જૂનાગઢમાં ત્રણ ગુફા સમૂહ, ખંભાલીડા ગુફા (રાજકોટથી 70 કિમી દૂર), તળાજા ગુફા (ભાવનગરમાં), સાણા ગુફા (ગિર સોમનાથમાં), ઢાંક ગુફા (રાજકોટ), ઝીંઝુરીઝર (સિદસરની ખીણમાં), કચ્છની ખાપરા કોડિયાની ગુફાઓ, કડિયાડુંગર ગુફા (ભરૂચ) વગેરે વિવિધ સમયગાળાના બૌદ્ધ અને હિંદુ ધર્મોના મહત્વપૂર્ણ સ્થાપત્ય નમૂનાઓ છે.”  \n\n11. રથમંદિર  \n- નિર્માણ પદ્ધતિ: “દક્ષિણ ભારતમાં એક પથ્થરમાંથી કે ખડકમાંથી કોતરીને બનાવેલ જગવિખ્યાત રથમંદિર પલ્લવ યુગની આગવી ઓળખ છે. કાંચીનું કૈલાસનાથનું અને વૈંકટપેરૂમલનું મંદિર કલા સ્થાપત્યનું શ્રેષ્ઠ ઉદાહરણ છે. દરેક રથમંદિર એક જ ખડક કાપીને બનાવવામાં આવ્યા છે.”  \n- મુખ્ય રથમંદિર: “સૌથી મોટું રથમંદિર ધર્મરાજનું અને નાનું રથમંદિર દ્રૌપદીનું છે.”\n\n12. મંદિર સ્થાપત્ય (મંદિરો)  \n- સામાન્ય લક્ષણો: “મંદિર સ્થાપત્યમાં ઊંચી પીઠિકાઓ ઉપર સીડીઓવાળાં અને શિખરબદ્ધ મંદિરો જોવા મળે છે. કેટલીક સપાટ મંદિર છે. ગર્ભગૃહની આસપાસ પ્રદક્ષિણા પથ રાખવામાં આવે છે.”  \n- પ્રસિદ્ધ મંદિરો: “જબલપુરનું ભૂમરાનું શિવમંદિર, દક્ષિણ ભારતનું લારખાનનું મંદિર, નાલંદા (સુલતાનગંજ)ની ભગવાન બુદ્ધની રથમંદિર, તામ્રમૂર્તિઓ તથા મથુરાના જૈન મંદિરની પ્રતિમા શિલ્પકલાક્ષેત્રે અદ્વિતીય છે. પલ્લવ રાજાઓનું મોટું યોગદાન છે; પલ્લવોની રાજધાની કાંચીમાં બંધાયેલાં મંદિરો અત્યંત પ્રસિદ્ધ છે.”  \n\n13. ગોપુરમ્‌ (મંદિરનું પ્રવેશદ્વાર)  \n- વ્યાખ્યા અને મહત્વ: “‘ગોપુરમ્‌’ એટલે મંદિરનું પ્રવેશદ્વાર. દક્ષિણ ભારતના પાંડ્ય શાસકોએ મંદિર નિર્માણ વેગવંતુ બનાવ્યું. તેમણે મંદિરની બહાર ઊભી દીવાલો અને ઊંચા સુંદર સુશોભિત દરવાજાઓની રચના કરી. આ મંદિરના દરવાજાઓ ‘ગોપુરમ્‌’ તરીકે ઓળખાય છે.”  \n- ઉદાહરણો: “કાંચી અને મદુરાઈના મંદિરોના ‘ગોપુરમ્‌’ દૂરથી જોઈને આજે પણ કલા રસિકો મંત્રમુગ્ધ બની જાય છે.”  \n\n14. દક્ષિણ ભારતીય મંદિરનું રેખાચિત્ર  \n- ઘટકો: “ગર્ભગૃહ મુખ્યત્વે એક નાનો અને અંધકારયુક્ત ઓરડો હોય છે, જેમાં મંદિરની પ્રતિમાને સ્થાપિત કરવામાં આવે છે. ગોપુરમ્‌ સ્થાપત્ય ઉપરથી અર્ધગોળાકાર હોય છે. મંડપ સ્તંભો ઉપર રચાયેલ મોટો હોલ અથવા મંદિરના મુખ્ય દ્વારની સામે રચાયેલ વિશાળ વિસ્તાર છે. શિખર ગર્ભગૃહના સૌથી ઊંચાણવાળા બાહ્ય ભાગ ઉપર અણીદાર બનાવવામાં આવેલી આકૃતિને કહે છે, જેને પિત્તળ કે સોનાથી મઢવામાં આવે છે. વિમાનો (મંદિરનો જ એક ભાગ) વર્ગાકાર અથવા ઢોળાવ આકારમાં રચવામાં આવે છે, જે ઘણા માળ સાથે પિરામિડ જેવા હોય છે અને ઉપરનો ભાગ શિખર હોય છે.”",
  "headings": [],
  "chapter_titles": [
    "ભારતનો સાંસ્કૃતિક વારસો : શિલ્પ અને સ્થાપત્ય",
    "ઉપલું નગર પણ રક્ષણાત્મક દીવાલોથી",
    "નીચલા નગરનાં મકાનો મુખ્યત્વે હાથે ઘડેલી",
    "મોહેં-જો-દડો નગર રચના જો-દડોનો અર્થ “મરેલાંનો ટેકરો' એવો થાય છે",
    "ધોળાવીરા",
    "sai waleatl કોતરેલા શિલાલેખો 3.5 સારનાથની સિંહાકૃતિ",
    "માઈલ દૂર આવેલા બર્બરના પહાડની ત્રણ ગુકાઓની દીવાલો પર કોતરાયેલા છે. તેમાં સમ્રાટ અશોકે આજીવન",
    "ફૂટ ઊંચો એક સિંહ સ્તંભ છે. સ્તંભના શિરો ભાગે બે શરીરવાળી અને એક મુખવાળી સિંહાકૃતિ છે",
    "દક્ષિણ ભારતીય મંદિરનું રેખાચિત્ર",
    "કોણાર્કનું સૂર્યમંદિર તેમ જ ભવ્યાતિભવ્ય એવાં આ મંદિરોની શૈલી બીજાં મંદિરો",
    "વડનગરનું કીર્તિતોરણ",
    "સોમનાથનું મંદિર",
    "ભારતમાં આવેલ એતિહાસિક સ્થળોની યાદી તૈયાર કરો",
    "ભારતનાં સ્થાપત્યનાં એતિહાસિક ચિત્રો એકત્રિત કરી આલબમ તૈયાર કરો",
    "લોથલ, ધોળાવીરા તથા મોઢેરાના સૂર્યમંદિરની મુલાકાત ગોઠવો",
    "તમારા વિસ્તારમાં આવેલા એતિહાસિક સ્થળોની મુલાકાત લઈ વર્ગખંડમાં તેની ચર્ચા કરો"
  ],
  "chapter_title": "ભારતનો સાંસ્કૃતિક વારસો : શિલ્પ અને સ્થાપત્ય",
  "excerpt": "3 ભારતનો સાંસ્કૃતિક વારસો : શિલ્પ અને સ્થાપત્ય\n\nભારત તેના સમૃદ્ધ સાંસ્કૃતિક વારસાના કારણે વિશ્વભરમાં જાણીતું છે. શિલ્પ અને સ્થાપત્યની\nવિવિધતાએ ભારતના ઇતિહાસને નવી ઓળખ આપી છે. ભારતનું પ્રાચીન સિંધુકાલીન નગર\nઆયોજન સમકાલીન વિશ્વના નગર આયોજન કરતાં ચડીયાતું હતું, તેની ગૌરવભેર નોંધ લઈ શકાય.\nhe 13४97\n\n=e\n\nશિલ્પી પોતાનાં કૌશલ્ય અને આવડતને છીણી - હથોડી વડે વિવિધ પ્રકારના મનના ભાવો પથ્થર, લાકડું કે ધાતુમાં\nકંડારે તે કલા એટલે શિલ્પકલા.\nસ્થાપત્ય\n\nસ્થાપત્યનો સરળ અર્થ બાંધકામ એવો થાય છે. સંસ્કૃત ભાષામાં સ્થાપત્ય માટે ‘ard? શબ્દ વપરાય છે, જે ખૂબ\nજ પ્રચલિત છે. આ અર્થમાં મકાનો, નગરો, કૂવાઓ, કિલ્લાઓ, મિનારાઓ, મંદિરો, મસ્જિદો, મકબરાઓ વગેરેના\nબાંધકામને “સ્થાપત્ય' કહે છે. સ્થાપત્યકલામાં 'સ્થપતિ'નું કૌશલ્ય પ્રયોજાય છે.\nપ્રાચીન ભારતનું નગર આયોજન\n\nભારત પ્રાચીન સમયથી નગર આયોજનમાં નિપુણતા ધરાવે છે. પુરાતત્ત્વીય ઉત્ખનન કરતાં આવાં ઘણાં નગરો\nમળી આવ્યાં છે. આ નગરોના મુખ્ય ત્રણ વિભાગો પડે છે : (1) શાસક અધિકારીઓનો ગઢ (સિટડલ) (2) અન્ય\nઅધિકારીઓના આવાસો ધરાવતું ઉપલું નગર (3) सामान्य નગરજનોના આવાસ ધરાવતું lad નગર.\ni # શા",
  "topics": [
    {
      "title": "ભારતનો સાંસ્કૃતિક વારસો : શિલ્પ અને સ્થાપત્ય",
      "summary": "",
      "subtopics": [
        {
          "title": "શિલ્પકલા",
          "narration": "“શિલ્પી પોતાનાં કૌશલ્ય અને આવડતને છીણી‑હથોડી વડે વિવિધ પ્રકારના મનના ભાવો પથ્થર, લાકડું કે ધાતુમાં કંડારે તે કલા એટલે શિલ્પકલા.”"
        },
        {
          "title": "સ્થાપત્ય",
          "narration": "“સ્થાપત્યનો સરળ અર્થ બાંધકામ એવો થાય છે. સંસ્કૃત ભાષામાં સ્થાપત્ય માટે ‘ard? શબ્દ વપરાય છે, જે ખૂબ જ પ્રચલિત છે. આ અર્થમાં મકાનો, નગરો, કૂવાઓ, કિલ્લાઓ, મિનારાઓ, મંદિરો, મસ્જિદો, મકબરાઓ વગેરેના બાંધકામને ‘સ્થાપત્ય' કહે છે. સ્થાપત્યકલામાં ‘સ્થપતિ’નું કૌશલ્ય પ્રયોજાય છે.”"
        }
      ],
      "topic_id": "1"
    },
    {
      "title": "પ્રાચીન ભારતનું નગર આયોજન",
      "summary": "",
      "subtopics": [
        {
          "title": "મુખ્ય વિભાગો",
          "narration": "“આ નગરોના મુખ્ય ત્રણ વિભાગો પડે છે : (1) શાસક અધિકારીઓનો ગઢ (સિટડલ) (2) અન્ય અધિકારીઓના આવાસો ધરાવતું ઉપલું નગર (3) સામાન્ય નગરજનોના આવાસ ધરાવતું lad નગર.”"
        },
        {
          "title": "ગઢ અને ઉપલું નગર",
          "narration": "“શાસક અધિકારીઓનો ગઢ જે ઊંચાઈ ઉપર બાંધવામાં આવ્યો છે. ઉપલું નગર પણ રક્ષણાત્મક દીવાલોથી સુરક્ષિત છે. અહીંથી બેથી પાંચ ઓરડાવાળા મકાનો મળી આવ્યા છે.”"
        },
        {
          "title": "નગરની રચના",
          "narration": "“નીચલા નગરનાં મકાનો મુખ્યત્વે હાથે ઘડેલી ઈંટોનાં બનાવેલાં છે.”"
        }
      ],
      "topic_id": "2"
    },
    {
      "title": "મોહેં‑જો‑દડો",
      "summary": "",
      "subtopics": [
        {
          "title": "નગર રચના",
          "narration": "“મોહેં‑જો‑દડો નગર આયોજનની દૃષ્ટિએ શ્રેષ્ઠ હતું. મકાનો પૂર અને ભેજથી બચવા ઊંચી પ્લિંથ (પીઠિકા) ઉપર બાંધવામાં આવતાં હતાં. શ્રીમંતોનાં મકાનો બે માળવાળા અને પાંચ કે સાત ઓરડાવાળા હતાં. સામાન્ય વર્ગનાં મકાનો એક માળ અને બે કે ત્રણ ઓરડાવાળા હતાં.”"
        },
        {
          "title": "રસ્તાઓ",
          "narration": "“મોટે ભાગે 9.75 મીટર પહોળા રસ્તાઓ હતા. નાના‑મોટા રસ્તાઓ કાટખૂણે મળતા અને એકથી વધુ વાહનો પસાર થાય એટલા પહોળા હતા. નગરના સીધા પહોળા રાજમાર્ગો હતા, જે ક્યાંય વળાંક ન લેતાં સીધા જ જતા હતા.”"
        },
        {
          "title": "ગટર યોજના",
          "narration": "“નગરમાંથી ગંદા પાણીના નિકાલ માટે ગટર બનાવવામાં આવી હતી. દરેક મકાનમાં એક ખાળકૂવો હતો. આ સુવ્યવસ્થિત ગટર યોજના પરથી લાગે છે કે તેઓ સ્વચ્છતા તેમજ આરોગ્યના ઊંચા ખ્યાલો ધરાવતા હતા.”"
        },
        {
          "title": "જાહેર સ્નાનાગાર",
          "narration": "“વિશાળ સ્નાનાગાર મળી આવ્યું છે. સ્નાનકુંડમાં સ્વચ્છ પાણી દાખલ કરવા અને ગંદું પાણી બહાર કાઢવા માટેની વ્યવસ્થા હતી. ગરમ પાણીની વ્યવસ્થા અને વસ્ત્રો બદલવા માટે ઓરડીઓ મળી આવી છે.”"
        },
        {
          "title": "જાહેર મકાનો",
          "narration": "“મોહેં‑જો‑દડોમાંથી જાહેર ઉપયોગી બે મકાનો મળ્યાં છે. તેનો ઉપયોગ સભાખંડ, મનોરંજન ખંડ, વહીવટ ખંડ કે રાજ્યના કોઠાર ખંડ તરીકે થતો હશે. મકાનોની એક હરોળ સૈનિકો માટેની બેરેક હતી.”"
        }
      ],
      "topic_id": "3"
    },
    {
      "title": "હડપ્પા",
      "summary": "",
      "subtopics": [
        {
          "title": "હડપ્પીય સંસ્કૃતિ",
          "narration": "“સૌપ્રથમ આ સંસ્કૃતિના અવશેષો હડપ્પા સ્થળેથી મળી આવેલા હોવાથી તેને હડપ્પીય સંસ્કૃતિ કહેવાય છે. આ સ્થળેથી પાષાણનાં અને તાંબાનાં ઓજારો, ચીજવસ્તુઓ વગેરે મળી આવ્યાં છે. તેથી તેને તામ્રપાષાણ યુગની સંસ્કૃતિ પણ કહે છે.”"
        },
        {
          "title": "નગર આયોજન",
          "narration": "“હડપ્પીય સમયનું નગરોનું આયોજન સુવ્યવસ્થિત હતું. તેના મોટા કોઠારો અને કિલ્લેબંધી નોંધપાત્ર છે. તેઓ અલંકારો ધારણ કરવાના શોખીન હતા, તેવા પુરાવાઓ મળ્યા છે.”"
        }
      ],
      "topic_id": "4"
    },
    {
      "title": "ધોળાવીરા",
      "summary": "",
      "subtopics": [
        {
          "title": "નગર અને કિલ્લાબંધી",
          "narration": "“ધોળાવીરાના કિલ્લા, મહેલ તેમજ નગરની મુખ્ય અવશેષો મળી આવ્યા છે. નગરની કિલ્લેબંધીની મજબૂત સુરક્ષા વ્યવસ્થા છે. આ દીવાલ માટી, પથ્થર અને ઈંટોમાંથી બનેલી છે.”"
        },
        {
          "title": "પાણીની વ્યવસ્થા",
          "narration": "“અહીંથી પીવાનું પાણી શુદ્ધ ગળાઈને આવે તેવી વ્યવસ્થા કરવામાં આવી હતી, જે આજના આધુનિક યુગમાં પણ મુશ્કેલ છે.”"
        }
      ],
      "topic_id": "5"
    },
    {
      "title": "લોથલ",
      "summary": "",
      "subtopics": [
        {
          "title": "બંદર અને વેપાર",
          "narration": "“લોથલ ધોળકા તાલુકામાં બે નદીઓના વચ્ચે આવેલું છે. નગરના પૂર્વ છેડે નીચાણવાળા ભાગમાં વહાણ લાંગરવા માટે મોટો ડોક્યાર્ડ બાંધવામાં આવ્યો હતો. આ ડોક્યાર્ડ, Wharf, દુકાનો, આયાત‑નિકાસના પુરાવા દર્શાવે છે કે લોથલ તે સમયનું સમૃદ્ધ બંદર હતું.”"
        }
      ],
      "topic_id": "6"
    },
    {
      "title": "મૌર્ય કાલીન કલા",
      "summary": "",
      "subtopics": [
        {
          "title": "સ્તૂપ",
          "narration": "“સ્તૂપ એટલે ભગવાન બુદ્ધના દેહાવશેષોને એક પાત્રમાં મૂકી તેના પર અર્ધગોળાકાર ઇમારતો બનાવવામાં આવે છે. અશોકના સમયના પાંચ સ્તૂપો જાણીતા છે: સાંચીનો, સારનાથનો, બેરતનો, નંદનગઢનો અને ગુજરાતમાં દેવની મોરીનો સ્તૂપ.”"
        },
        {
          "title": "હર્મિકા, મેધિ, પ્રદક્ષિણા પથ, તોરણ, સ્તંભલેખો",
          "narration": "“સ્તૂપની અંડાકાર ભાગની ટોચની ચારે બાજુએ આવેલી રેલિંગને ‘હર્મિકા’ કહે છે. સ્તૂપની ચારે બાજુએ ઊંચા ગોળાકાર રસ્તાને ‘AB’ કહે છે. ગોળાકાર રસ્તાને ‘પ્રદક્ષિણા પથ’ કહે છે. તોરણ એટલે બે સ્તંભ ઉપર સીધા પાટડા કે કમાનના આકારમાં પથ્થર આડા પાડી કરવામાં આવેલું સુંદર સ્થાપત્ય. સ્તંભલેખો એક જ શિલામાંથી કોતરવામાં આવ્યા છે, જેમ કે અશોકના ધર્માજ્ઞાઓ કોતરેલા સ્તંભો.”"
        }
      ],
      "topic_id": "7"
    },
    {
      "title": "દક્ષિણ ભારતની દ્રવિડ શૈલી",
      "summary": "",
      "subtopics": [
        {
          "title": "બૌદ્ધ સ્તૂપો",
          "narration": "“દક્ષિણ ભારતમાં કૃષ્ણા અને ગોદાવરી નદીઓની આસપાસના વિસ્તારમાં સાતવાહન વંશના રાજાઓના સમય દરમિયાન અનેક બૌદ્ધ સ્તૂપો બંધાયા હતા. નાગાર્જુન કોંડાનો સ્તૂપ અને અમરાવતીનો સ્તૂપ દ્રવિડ શૈલીના સર્વશ્રેષ્ઠ નમૂનાઓ છે.”"
        }
      ],
      "topic_id": "8"
    },
    {
      "title": "ગુપ્તકાલીન કલા",
      "summary": "",
      "subtopics": [
        {
          "title": "મુખ્ય સ્મારકો",
          "narration": "“જબલપુરનું (નિનાવા) પાર્વતી મંદિર, ભૂમરા (નાગોડા)નું શિવમંદિર, એરણ (મધ્યપ્રદેશ)નું નૃસિંહ મંદિર, જામનગરનું ગોપમંદિર, Aul ચૈત્યો, મઠો, વિહારો, ધ્વજ, સ્તંભો વગેરે ગુપ્તયુગની કલાઓના નમૂના છે.”"
        },
        {
          "title": "શિલ્પ",
          "narration": "“સારનાથની બુદ્ધ પ્રતિમાઓ, મથુરાની વિષ્ણુ પ્રતિમા, મહાવીર સ્વામીની પ્રતિમા, ઉદયગિરિની ગુફાની, વિષ્ણુના વરાહ સ્વરૂપની પ્રતિમા વગેરે ભારતીય ગુપ્તકાલીન કલાના સર્વોત્તમ નમૂનાઓને લીધે ગુપ્તયુગ કલાનો ‘સુવર્ણયુગ’ કહેવાય છે.”"
        }
      ],
      "topic_id": "9"
    },
    {
      "title": "ગુફા સ્થાપત્ય (ગુફાઓ)",
      "summary": "",
      "subtopics": [
        {
          "title": "પ્રસિદ્ધ ગુફાઓ",
          "narration": "“ઔરંગાબાદ પાસે આવેલ અજંતા‑ઈલોરાની ગુફાઓ, મુંબઈ પાસેની એલિફન્ટાની ગુફાઓ, ઓડિશામાં ભુવનેશ્વરની પશ્ચિમે ઉદયગિરિ, ખંડગિરિ ગુફાઓ, મધ્યપ્રદેશની બાઘની ગુફાઓ, ગુપ્તકાલીન ગુફાસ્થાપત્યના પ્રસિદ્ધ નમૂનાઓ છે.”"
        },
        {
          "title": "ગુજરાતની ગુફાઓ",
          "narration": "“જૂનાગઢમાં ત્રણ ગુફા સમૂહ, ખંભાલીડા ગુફા (રાજકોટથી 70 કિમી દૂર), તળાજા ગુફા (ભાવનગરમાં), સાણા ગુફા (ગિર સોમનાથમાં), ઢાંક ગુફા (રાજકોટ), ઝીંઝુરીઝર (સિદસરની ખીણમાં), કચ્છની ખાપરા કોડિયાની ગુફાઓ, કડિયાડુંગર ગુફા (ભરૂચ) વગેરે વિવિધ સમયગાળાના બૌદ્ધ અને હિંદુ ધર્મોના મહત્વપૂર્ણ સ્થાપત્ય નમૂનાઓ છે.”"
        }
      ],
      "topic_id": "10"
    },
    {
      "title": "રથમંદિર",
      "summary": "",
      "subtopics": [
        {
          "title": "નિર્માણ પદ્ધતિ",
          "narration": "“દક્ષિણ ભારતમાં એક પથ્થરમાંથી કે ખડકમાંથી કોતરીને બનાવેલ જગવિખ્યાત રથમંદિર પલ્લવ યુગની આગવી ઓળખ છે. કાંચીનું કૈલાસનાથનું અને વૈંકટપેરૂમલનું મંદિર કલા સ્થાપત્યનું શ્રેષ્ઠ ઉદાહરણ છે. દરેક રથમંદિર એક જ ખડક કાપીને બનાવવામાં આવ્યા છે.”"
        },
        {
          "title": "મુખ્ય રથમંદિર",
          "narration": "“સૌથી મોટું રથમંદિર ધર્મરાજનું અને નાનું રથમંદિર દ્રૌપદીનું છે.”"
        }
      ],
      "topic_id": "11"
    },
    {
      "title": "મંદિર સ્થાપત્ય (મંદિરો)",
      "summary": "",
      "subtopics": [
        {
          "title": "સામાન્ય લક્ષણો",
          "narration": "“મંદિર સ્થાપત્યમાં ઊંચી પીઠિકાઓ ઉપર સીડીઓવાળાં અને શિખરબદ્ધ મંદિરો જોવા મળે છે. કેટલીક સપાટ મંદિર છે. ગર્ભગૃહની આસપાસ પ્રદક્ષિણા પથ રાખવામાં આવે છે.”"
        },
        {
          "title": "પ્રસિદ્ધ મંદિરો",
          "narration": "“જબલપુરનું ભૂમરાનું શિવમંદિર, દક્ષિણ ભારતનું લારખાનનું મંદિર, નાલંદા (સુલતાનગંજ)ની ભગવાન બુદ્ધની રથમંદિર, તામ્રમૂર્તિઓ તથા મથુરાના જૈન મંદિરની પ્રતિમા શિલ્પકલાક્ષેત્રે અદ્વિતીય છે. પલ્લવ રાજાઓનું મોટું યોગદાન છે; પલ્લવોની રાજધાની કાંચીમાં બંધાયેલાં મંદિરો અત્યંત પ્રસિદ્ધ છે.”"
        }
      ],
      "topic_id": "12"
    },
    {
      "title": "ગોપુરમ્‌ (મંદિરનું પ્રવેશદ્વાર)",
      "summary": "",
      "subtopics": [
        {
          "title": "વ્યાખ્યા અને મહત્વ",
          "narration": "“‘ગોપુરમ્‌’ એટલે મંદિરનું પ્રવેશદ્વાર. દક્ષિણ ભારતના પાંડ્ય શાસકોએ મંદિર નિર્માણ વેગવંતુ બનાવ્યું. તેમણે મંદિરની બહાર ઊભી દીવાલો અને ઊંચા સુંદર સુશોભિત દરવાજાઓની રચના કરી. આ મંદિરના દરવાજાઓ ‘ગોપુરમ્‌’ તરીકે ઓળખાય છે.”"
        },
        {
          "title": "ઉદાહરણો",
          "narration": "“કાંચી અને મદુરાઈના મંદિરોના ‘ગોપુરમ્‌’ દૂરથી જોઈને આજે પણ કલા રસિકો મંત્રમુગ્ધ બની જાય છે.”"
        }
      ],
      "topic_id": "13"
    },
    {
      "title": "દક્ષિણ ભારતીય મંદિરનું રેખાચિત્ર",
      "summary": "",
      "subtopics": [
        {
          "title": "ઘટકો",
          "narration": "“ગર્ભગૃહ મુખ્યત્વે એક નાનો અને અંધકારયુક્ત ઓરડો હોય છે, જેમાં મંદિરની પ્રતિમાને સ્થાપિત કરવામાં આવે છે. ગોપુરમ્‌ સ્થાપત્ય ઉપરથી અર્ધગોળાકાર હોય છે. મંડપ સ્તંભો ઉપર રચાયેલ મોટો હોલ અથવા મંદિરના મુખ્ય દ્વારની સામે રચાયેલ વિશાળ વિસ્તાર છે. શિખર ગર્ભગૃહના સૌથી ઊંચાણવાળા બાહ્ય ભાગ ઉપર અણીદાર બનાવવામાં આવેલી આકૃતિને કહે છે, જેને પિત્તળ કે સોનાથી મઢવામાં આવે છે. વિમાનો (મંદિરનો જ એક ભાગ) વર્ગાકાર અથવા ઢોળાવ આકારમાં રચવામાં આવે છે, જે ઘણા માળ સાથે પિરામિડ જેવા હોય છે અને ઉપરનો ભાગ શિખર હોય છે.”"
        }
      ],
      "topic_id": "14"
    },
    {
      "title": "સ્થાપત્ય શબ્દનું સંસ્કૃત મૂળ અને અર્થ",
      "summary": "સંસ્કૃતમાં 'અર્ધ' શબ્દ સ્થાપત્ય માટે વપરાય છે, જે બાંધકામ અને નિર્માણની કલાને દર્શાવે છે. આ શબ્દની સમજ સ્થાપત્ય કળાના મૂળભૂત સિદ્ધાંતોને સ્પષ્ટ કરે છે.",
      "supporting_quote": "સ્થાપત્યનો સરળ અર્થ બાંધકામ એવો થાય છે. સંસ્કૃત ભાષામાં સ્થાપત્ય માટે ‘ard? શબ્દ વપરાય છે, જે ખૂબ જ પ્રચલિત છે.",
      "is_assistant_generated": true,
      "subtopics": [],
      "topic_id": "15"
    },
    {
      "title": "પ્રાચીન ભારતીય કિલ્લાઓ અને ગઢોની રચના",
      "summary": "પ્રાચીન કિલ્લાઓ અને ગઢો નગર આયોજનમાં શાસક અધિકારીઓના ગઢ તરીકે મહત્વપૂર્ણ હતા. તેમની રચનામાં કિલ્લા, દીવાલો, અને સુરક્ષા વ્યવસ્થાઓનો સમાવેશ થાય છે.",
      "supporting_quote": "પ્રાચીન ભારતનું નગર આયોજન ... (1) શાસક અધિકારીઓનો ગઢ (સિટડલ) ...",
      "is_assistant_generated": true,
      "subtopics": [],
      "topic_id": "16"
    }
  ]
}